pycityproto/__init__.py
pycityproto/__init__.pyi
pycityproto/city/__init__.py
pycityproto/city/__init__.pyi
pycityproto/city/clock/__init__.py
pycityproto/city/clock/__init__.pyi
pycityproto/city/clock/v1/__init__.py
pycityproto/city/clock/v1/__init__.pyi
pycityproto/city/clock/v1/clock_service_pb2.py
pycityproto/city/clock/v1/clock_service_pb2.pyi
pycityproto/city/clock/v1/clock_service_pb2_grpc.py
pycityproto/city/comm/__init__.py
pycityproto/city/comm/__init__.pyi
pycityproto/city/comm/input/__init__.py
pycityproto/city/comm/input/__init__.pyi
pycityproto/city/comm/input/v1/__init__.py
pycityproto/city/comm/input/v1/__init__.pyi
pycityproto/city/comm/input/v1/comm_pb2.py
pycityproto/city/comm/input/v1/comm_pb2.pyi
pycityproto/city/comm/input/v1/comm_pb2_grpc.py
pycityproto/city/comm/interaction/__init__.py
pycityproto/city/comm/interaction/__init__.pyi
pycityproto/city/comm/interaction/aoi/__init__.py
pycityproto/city/comm/interaction/aoi/__init__.pyi
pycityproto/city/comm/interaction/aoi/v1/__init__.py
pycityproto/city/comm/interaction/aoi/v1/__init__.pyi
pycityproto/city/comm/interaction/aoi/v1/aoi_service_pb2.py
pycityproto/city/comm/interaction/aoi/v1/aoi_service_pb2.pyi
pycityproto/city/comm/interaction/aoi/v1/aoi_service_pb2_grpc.py
pycityproto/city/comm/interaction/demand/__init__.py
pycityproto/city/comm/interaction/demand/__init__.pyi
pycityproto/city/comm/interaction/demand/v1/__init__.py
pycityproto/city/comm/interaction/demand/v1/__init__.pyi
pycityproto/city/comm/interaction/demand/v1/demand_service_pb2.py
pycityproto/city/comm/interaction/demand/v1/demand_service_pb2.pyi
pycityproto/city/comm/interaction/demand/v1/demand_service_pb2_grpc.py
pycityproto/city/comm/interaction/gateway/__init__.py
pycityproto/city/comm/interaction/gateway/__init__.pyi
pycityproto/city/comm/interaction/gateway/v1/__init__.py
pycityproto/city/comm/interaction/gateway/v1/__init__.pyi
pycityproto/city/comm/interaction/gateway/v1/gateway_pb2.py
pycityproto-2.4.5.dist-info/licenses/LICENSE
pycityproto-2.4.5.dist-info/METADATA
pycityproto-2.4.5.dist-info/WHEEL
pycityproto-2.4.5.dist-info/top_level.txt
pycityproto-2.4.5.dist-info/RECORD
