Metadata-Version: 2.4
Name: pycityproto
Version: 2.4.5
Summary: City Proto Generated Python SDK
Author-email: Jun Zhang <zhangjun990222@gmail.com>, Junbo Yan <yanjb20thu@gmali.com>
License: MIT License
Project-URL: Homepage, https://github.com/tsinghua-fib-lab/cityproto
Project-URL: Documentation, https://cityproto.sim.fiblab.net/
Project-URL: Repository, https://github.com/tsinghua-fib-lab/cityproto.git
Project-URL: Issues, https://github.com/tsinghua-fib-lab/cityproto/issues
Keywords: city,proto,protobuf
Classifier: Programming Language :: Python :: 3
Classifier: Operating System :: OS Independent
Requires-Python: >=3.8
License-File: LICENSE
Requires-Dist: importlib-metadata; python_version < "3.8"
Requires-Dist: grpcio<2.0.0,>=1.60.0
Requires-Dist: protobuf<6.0.0,>=4.24.0
Requires-Dist: types-protobuf<6.0.0,>=4.24.0
Dynamic: license-file
